README.md
setup.py
human_security/__init__.py
human_security.egg-info/PKG-INFO
human_security.egg-info/SOURCES.txt
human_security.egg-info/dependency_links.txt
human_security.egg-info/not-zip-safe
human_security.egg-info/top_level.txt