Metadata-Version: 1.2
Name: human-security
Version: 1.0
Summary: Provides easy to use API the RSA and AES
Home-page: https://github.com/mdipierro/human_security
Author: Massimo Di Pierro
Author-email: massimo.dipierro@gmail.com
Maintainer: Massimo Di Pierro
Maintainer-email: massimo.dipierro@gmail.com
License: BSD
Platform: any
Classifier: Development Status :: 5 - Production/Stable
Classifier: Programming Language :: Python :: 3
Classifier: Topic :: Software Development :: Libraries :: Python Modules
